schemdule/__init__.py
schemdule/__main__.py
schemdule/timeutils.py
schemdule/configurations/__init__.py
schemdule/configurations/globals.py
schemdule/extensions/__init__.py
schemdule/helpers/__init__.py
schemdule/prompters/__init__.py
schemdule/prompters/builders.py
schemdule/prompters/general.py
schemdule/prompters/hubs.py
schemdule/schedulers/__init__.py
schemdule/schemas/__init__.py
schemdule/schemas/timetable.py
schemdule-0.1.0.dist-info/METADATA
schemdule-0.1.0.dist-info/WHEEL
schemdule-0.1.0.dist-info/entry_points.txt
schemdule-0.1.0.dist-info/top_level.txt
schemdule-0.1.0.dist-info/RECORD
