Metadata-Version: 2.1
Name: schemdule
Version: 0.1.0
Summary: A tiny tool using script as schema to schedule one day and remind you to do something during a day.
Home-page: https://github.com/StardustDL/schemdule
Author: StardustDL
Author-email: stardustdl@163.com
License: UNKNOWN
Project-URL: Source Code, https://github.com/StardustDL/schemdule
Project-URL: Changes, https://github.com/StardustDL/schemdule/releases
Project-URL: Documentation, https://github.com/StardustDL/schemdule
Project-URL: Bug Tracker, https://github.com/StardustDL/schemdule/issues
Platform: UNKNOWN
Classifier: License :: OSI Approved :: Mozilla Public License 2.0 (MPL 2.0)
Classifier: Operating System :: OS Independent
Classifier: Programming Language :: Python :: 3
Classifier: Programming Language :: Python :: 3.7
Classifier: Programming Language :: Python :: 3.8
Classifier: Programming Language :: Python :: 3.9
Classifier: Programming Language :: Python :: Implementation :: CPython
Classifier: Topic :: Utilities
Requires-Python: >=3.7
Requires-Dist: click (>=8.0.1)
Requires-Dist: enlighten (>=1.10.1)
